goldteeth/__init__.py
goldteeth/alert.wav
goldteeth-1.1.1.dist-info/licenses/LICENSE
goldteeth-1.1.1.dist-info/METADATA
goldteeth-1.1.1.dist-info/WHEEL
goldteeth-1.1.1.dist-info/entry_points.txt
goldteeth-1.1.1.dist-info/top_level.txt
goldteeth-1.1.1.dist-info/RECORD
