Metadata-Version: 2.4
Name: goldteeth
Version: 1.1.1
Summary: Monitors crypto/stock prices or volatility and plays an alert sound when a target is reached
Author-email: "Will Foster (sadsfae)" <wfoster@pm.me>
License:                     GNU GENERAL PUBLIC LICENSE
Project-URL: Homepage, https://github.com/sadsfae/goldteeth
Project-URL: Repository, https://github.com/sadsfae/goldteeth
Project-URL: Issues, https://github.com/sadsfae/goldteeth/issues
Classifier: Programming Language :: Python :: 3
Classifier: Operating System :: OS Independent
Requires-Python: >=3.8
License-File: LICENSE
Requires-Dist: requests
Requires-Dist: pytz
Requires-Dist: websocket-client
Dynamic: license-file
